quri_parts/backend/__init__.py
quri_parts/backend/py.typed
quri_parts/backend/qubit_mapping.py
quri_parts/core/NOTICE
quri_parts/core/__init__.py
quri_parts/core/circuit/__init__.py
quri_parts/core/circuit/exp_commuting_paulis_gate.py
quri_parts/core/circuit/exp_single_pauli_gate.py
quri_parts/core/estimator/__init__.py
quri_parts/core/estimator/gradient.py
quri_parts/core/estimator/hessian.py
quri_parts/core/estimator/sampling/__init__.py
quri_parts/core/estimator/sampling/estimator.py
quri_parts/core/estimator/sampling/estimator_helpers.py
quri_parts/core/estimator/sampling/overlap_estimator.py
quri_parts/core/estimator/sampling/pauli.py
quri_parts/core/estimator/utils.py
quri_parts/core/measurement/__init__.py
quri_parts/core/measurement/bitwise_commuting_pauli.py
quri_parts/core/measurement/interface.py
quri_parts/core/operator/__init__.py
quri_parts/core/operator/conjugation.py
quri_parts/core/operator/grouping/__init__.py
quri_parts/core/operator/grouping/pauli_grouping.py
quri_parts/core/operator/operator.py
quri_parts/core/operator/pauli.py
quri_parts/core/operator/representation/__init__.py
quri_parts/core/operator/representation/bsf.py
quri_parts/core/operator/sparse.py
quri_parts/core/operator/trotter_suzuki.py
quri_parts/core/py.typed
quri_parts/core/sampling/__init__.py
quri_parts/core/sampling/shots_allocator.py
quri_parts/core/sampling/weighted_shots_allocator.py
quri_parts/core/state/__init__.py
quri_parts/core/state/comp_basis.py
quri_parts/core/state/state.py
quri_parts/core/state/state_helper.py
quri_parts/core/state/state_parametric.py
quri_parts/core/state/state_vector.py
quri_parts/core/state/state_vector_parametric.py
quri_parts/core/utils/__init__.py
quri_parts/core/utils/array.py
quri_parts/core/utils/binary_field.py
quri_parts/core/utils/bit.py
quri_parts/core/utils/concurrent.py
quri_parts/core/utils/differentiation.py
quri_parts/core/utils/recording.py
quri_parts/core/utils/statistics.py
quri_parts_core-17.0.0.dist-info/LICENSE
quri_parts_core-17.0.0.dist-info/METADATA
quri_parts_core-17.0.0.dist-info/WHEEL
quri_parts_core-17.0.0.dist-info/RECORD
